LICENSE
MANIFEST.in
README.md
requirements.txt
run_python_base_app_ldap_extension_test_suite.py
setup.py
python_base_app_ldap_extension/__init__.py
python_base_app_ldap_extension/git.py
python_base_app_ldap_extension/git_metadata.py
python_base_app_ldap_extension/ldap_user_handler.py
python_base_app_ldap_extension/settings.py
python_base_app_ldap_extension.egg-info/PKG-INFO
python_base_app_ldap_extension.egg-info/SOURCES.txt
python_base_app_ldap_extension.egg-info/dependency_links.txt
python_base_app_ldap_extension.egg-info/requires.txt
python_base_app_ldap_extension.egg-info/top_level.txt
python_base_app_ldap_extension/test/__init__.py
python_base_app_ldap_extension/test/test_git.py
python_base_app_ldap_extension/test/test_ldap_user_handler.py
python_base_app_ldap_extension/test/test_settings.py
python_base_app_ldap_extension/test/test_suite.py