Metadata-Version: 2.1
Name: python-base-app-ldap-extension
Version: 0.1.2
Summary: Support for LDAP authentication in python_base_app.
Home-page: https://github.com/marcus67/python_base_app_ldap_extension
Author: Marcus Rickert
Author-email: marcus.rickert@web.de
License: UNKNOWN
Platform: UNKNOWN
License-File: LICENSE
